CHANGES.txt
CONTRIBUTORS.txt
COPYRIGHT.txt
LICENSE.txt
MANIFEST.in
README.txt
setup.cfg
setup.py
collective/__init__.py
collective.groupspace.workflow.egg-info/PKG-INFO
collective.groupspace.workflow.egg-info/SOURCES.txt
collective.groupspace.workflow.egg-info/dependency_links.txt
collective.groupspace.workflow.egg-info/entry_points.txt
collective.groupspace.workflow.egg-info/namespace_packages.txt
collective.groupspace.workflow.egg-info/not-zip-safe
collective.groupspace.workflow.egg-info/paster_plugins.txt
collective.groupspace.workflow.egg-info/requires.txt
collective.groupspace.workflow.egg-info/top_level.txt
collective/groupspace/__init__.py
collective/groupspace/workflow/__init__.py
collective/groupspace/workflow/config.py
collective/groupspace/workflow/configure.zcml
collective/groupspace/workflow/handlers.py
collective/groupspace/workflow/interfaces.py
collective/groupspace/workflow/policy.py
collective/groupspace/workflow/setuphandlers.py
collective/groupspace/workflow/profiles/default/import_steps.xml
collective/groupspace/workflow/profiles/default/metadata.xml
collective/groupspace/workflow/profiles/default/workflows.xml
collective/groupspace/workflow/profiles/default/workflows/groupspace_content_workflow/definition.xml
collective/groupspace/workflow/profiles/default/workflows/groupspace_workflow/definition.xml
collective/groupspace/workflow/tests/__init__.py
collective/groupspace/workflow/tests/base.py
collective/groupspace/workflow/tests/placefulworkflowpolicy.txt
collective/groupspace/workflow/tests/test_functional.py
collective/groupspace/workflow/tests/test_handlers.py
collective/groupspace/workflow/tests/test_policy.py
collective/groupspace/workflow/tests/test_setuphandlers.py
collective/groupspace/workflow/tests/utils.py